fxbootstrap/__init__.py
fxbootstrap/cli.py
fxbootstrap-1.0.1.dist-info/METADATA
fxbootstrap-1.0.1.dist-info/RECORD
fxbootstrap-1.0.1.dist-info/WHEEL
fxbootstrap-1.0.1.dist-info/entry_points.txt
fxbootstrap-1.0.1.dist-info/top_level.txt
