Metadata-Version: 2.1
Name: fxbootstrap
Version: 1.0.1
Summary: Bootstrap launcher for Firefox
Home-page: https://github.com/davehunt/fxbootstrap
Author: Dave Hunt
Author-email: dhunt@mozilla.com
License: Mozilla Public License 2.0 (MPL 2.0)
Keywords: firefox test profile launch download install mozilla
Platform: UNKNOWN
Classifier: Development Status :: 5 - Production/Stable
Classifier: Intended Audience :: Developers
Classifier: License :: OSI Approved :: Mozilla Public License 2.0 (MPL 2.0)
Classifier: Operating System :: POSIX
Classifier: Operating System :: Microsoft :: Windows
Classifier: Operating System :: MacOS :: MacOS X
Classifier: Topic :: Software Development :: Quality Assurance
Classifier: Topic :: Software Development :: Testing
Classifier: Topic :: Utilities
Classifier: Programming Language :: Python
Classifier: Programming Language :: Python :: 2.7
Requires-Dist: backports-tempfile
Requires-Dist: click
Requires-Dist: crayons
Requires-Dist: halo
Requires-Dist: mozdownload
Requires-Dist: mozinstall
Requires-Dist: mozrunner
Requires-Dist: mozversion
